ai_twerk_generator/__init__.py
ai_twerk_generator-1768544.455.937.dist-info/licenses/LICENSE
ai_twerk_generator-1768544.455.937.dist-info/METADATA
ai_twerk_generator-1768544.455.937.dist-info/WHEEL
ai_twerk_generator-1768544.455.937.dist-info/top_level.txt
ai_twerk_generator-1768544.455.937.dist-info/RECORD
