Metadata-Version: 2.4
Name: ai-twerk-generator
Version: 1768544.455.937
Summary: High-quality integration for https://supermaker.ai/blog/how-to-make-ai-twerk-video-with-supermaker-ai-free-online/
Home-page: https://supermaker.ai/blog/how-to-make-ai-twerk-video-with-supermaker-ai-free-online/
Author: SuperMaker
Classifier: Programming Language :: Python :: 3
Classifier: License :: OSI Approved :: MIT License
Requires-Python: >=3.6
License-File: LICENSE
Dynamic: author
Dynamic: classifier
Dynamic: description
Dynamic: description-content-type
Dynamic: home-page
Dynamic: license-file
Dynamic: requires-python
Dynamic: summary
